ultimateraylib/__init__.py
ultimateraylib/_classes.py
ultimateraylib/audio.py
ultimateraylib/camera.py
ultimateraylib/collision.py
ultimateraylib/constants.py
ultimateraylib/draw.py
ultimateraylib/event.py
ultimateraylib/file.py
ultimateraylib/gui.py
ultimateraylib/image.py
ultimateraylib/libAppleSillicon.dylib
ultimateraylib/libEGL.dylib
ultimateraylib/libGLESv2.dylib
ultimateraylib/liblinux86_64.so
ultimateraylib/libraylib.dll.a
ultimateraylib/libwin86_64.dll
ultimateraylib/light.py
ultimateraylib/load.py
ultimateraylib/math.py
ultimateraylib/raylib.dll
ultimateraylib/rlgl.py
ultimateraylib/text.py
ultimateraylib/util.py
ultimateraylib/window.py
ultimateraylib-0.2.4.dist-info/METADATA
ultimateraylib-0.2.4.dist-info/WHEEL
ultimateraylib-0.2.4.dist-info/top_level.txt
ultimateraylib-0.2.4.dist-info/RECORD
