Metadata-Version: 2.4
Name: ultimateraylib
Version: 0.2.4
Summary: Python binding for Raylib, Raygui and Raymath
Author-email: Annes <anneswidow@gmail.com>
License: MIT
Project-URL: Homepage, https://github.com/yourusername/ultimateraylib
Project-URL: Bug Tracker, https://github.com/yourusername/ultimateraylib/issues
Keywords: raylib,graphics,3D,ctypes,python-wrapper
Classifier: Programming Language :: Python :: 3
Classifier: License :: OSI Approved :: MIT License
Classifier: Operating System :: MacOS :: MacOS X
Classifier: Operating System :: POSIX :: Linux
Classifier: Topic :: Software Development :: Libraries
Classifier: Topic :: Games/Entertainment :: Simulation
Requires-Python: >=3.8
